sequensign/__init__.py
sequensign/tools.py
sequensign-0.1.1.dist-info/licenses/LICENSE
sequensign-0.1.1.dist-info/METADATA
sequensign-0.1.1.dist-info/WHEEL
sequensign-0.1.1.dist-info/top_level.txt
sequensign-0.1.1.dist-info/RECORD
