Metadata-Version: 2.4
Name: sequensign
Version: 0.1.1
Summary: Handling digital signatures in sequence files
Author: Peter Vegh
License-Expression: GPL-3.0-or-later
Project-URL: Homepage, https://github.com/Edinburgh-Genome-Foundry/Sequensign
Keywords: biology,sequence,DNA
License-File: LICENSE
Requires-Dist: biopython
Dynamic: license-file
